MANIFEST.in
README.md
setup.py
simplepro/.DS_Store
simplepro/.core.so
simplepro/__init__.py
simplepro/action.py
simplepro/action.pyi
simplepro/apps.py
simplepro/conf.py
simplepro/decorators.py
simplepro/decorators.pyi
simplepro/dialog.py
simplepro/filters.py
simplepro/forms.py
simplepro/handlers.py
simplepro/middlewares.py
simplepro/urls.py
simplepro/utils.py
simplepro.egg-info/PKG-INFO
simplepro.egg-info/SOURCES.txt
simplepro.egg-info/dependency_links.txt
simplepro.egg-info/not-zip-safe
simplepro.egg-info/requires.txt
simplepro.egg-info/top_level.txt
simplepro/__pycache__/__init__.cpython-312.pyc
simplepro/bawa/views.py
simplepro/captcha/JetBrainsMono-Bold.ttf
simplepro/captcha/captcha.py
simplepro/captcha/views.py
simplepro/components/__init__.py
simplepro/components/fields.py
simplepro/components/fields.pyi
simplepro/components/utils.py
simplepro/components/widgets.py
simplepro/editor/__init__.py
simplepro/editor/fields.py
simplepro/editor/fields.pyi
simplepro/editor/utils.py
simplepro/editor/views.py
simplepro/editor/widgets.py
simplepro/group/utils.py
simplepro/group/view.py
simplepro/locale/.DS_Store
simplepro/locale/zh_Hans/.DS_Store
simplepro/locale/zh_Hans/LC_MESSAGES/django.mo
simplepro/locale/zh_Hans/LC_MESSAGES/django.po
simplepro/locale/zh_Hans/LC_MESSAGES/make.sh
simplepro/management/.DS_Store
simplepro/management/commands/migrate_menu.py
simplepro/monitor/test.py
simplepro/monitor/utils.py
simplepro/monitor/views.py
simplepro/static/.DS_Store
simplepro/static/admin/.DS_Store
simplepro/static/admin/bawa/BawaData.json
simplepro/static/admin/bawa/demo.html
simplepro/static/admin/bawa/index.html
simplepro/static/admin/bawa/render.common.js
simplepro/static/admin/bawa/render.umd.js
simplepro/static/admin/bawa/render.umd.min.js
simplepro/static/admin/bawa/charts/bar/basic.json
simplepro/static/admin/bawa/charts/bubble/smoking-rate.json
simplepro/static/admin/bawa/charts/bullet/basic.json
simplepro/static/admin/bawa/charts/calendar/basic.json
simplepro/static/admin/bawa/charts/column/basic.json
simplepro/static/admin/bawa/charts/donut/basic.json
simplepro/static/admin/bawa/charts/funnel/basic.json
