Metadata-Version: 2.1
Name: simplepro
Version: 7.20
Summary: django admin theme 后台模板
Home-page: https://github.com/newpanjing/simpleui
Author: panjing
Author-email: newpanjing@icloud.com
License: Apache License 2.0
Classifier: Programming Language :: Python :: 3
Classifier: Operating System :: OS Independent
Requires-Dist: django>=2.1
Requires-Dist: django-simpleui>=2025.05.16
Requires-Dist: django-import-export
Requires-Dist: requests
Requires-Dist: rsa
Requires-Dist: psutil
Requires-Dist: pillow
